pretty_pipeline/__init__.py
pretty_pipeline/pipeline.py
pretty_pipeline-0.0.3.dist-info/LICENSE
pretty_pipeline-0.0.3.dist-info/METADATA
pretty_pipeline-0.0.3.dist-info/WHEEL
pretty_pipeline-0.0.3.dist-info/top_level.txt
pretty_pipeline-0.0.3.dist-info/RECORD
