Metadata-Version: 2.1
Name: pretty-pipeline
Version: 0.0.3
Summary: Package for creating ETL pipelines.
Home-page: https://github.com/rob-dalton/pretty-pipeline
Author: Rob Dalton
License: UNKNOWN
Platform: UNKNOWN
Classifier: Programming Language :: Python :: 3
Classifier: License :: OSI Approved :: MIT License
Classifier: Operating System :: OS Independent
Requires-Python: >=3.8
